mesita/__init__.py
mesita/prettytable.py
mesita-0.0.1.dist-info/METADATA
mesita-0.0.1.dist-info/WHEEL
mesita-0.0.1.dist-info/RECORD
