Metadata-Version: 2.1
Name: mesita
Version: 0.0.1
Summary: Prints tables in terminal
License: MIT
Author: Matthew Powers
Author-email: matthewkevinpowers@gmail.com
Requires-Python: >=3.7
Classifier: License :: OSI Approved :: MIT License
Classifier: Programming Language :: Python :: 3
Classifier: Programming Language :: Python :: 3.7
Classifier: Programming Language :: Python :: 3.8
Classifier: Programming Language :: Python :: 3.9
Classifier: Programming Language :: Python :: 3.10
Classifier: Programming Language :: Python :: 3.11
